cosamp/__init__.py
cosamp/cosamp.py
cosamp-0.0.2.dist-info/LICENCE
cosamp-0.0.2.dist-info/METADATA
cosamp-0.0.2.dist-info/WHEEL
cosamp-0.0.2.dist-info/top_level.txt
cosamp-0.0.2.dist-info/RECORD
