Metadata-Version: 2.1
Name: cosamp
Version: 0.0.2
Summary: Python implementation of the CoSaMP algorithm
Home-page: UNKNOWN
Author: Renato Fuzaro Miotto
Author-email: <renato.fmiotto@gmail.com>
License: UNKNOWN
Keywords: python,sparse signal,cosamp
Platform: UNKNOWN
Classifier: Development Status :: 1 - Planning
Classifier: Intended Audience :: Developers
Classifier: Programming Language :: Python :: 3
Classifier: Operating System :: Unix
Classifier: Operating System :: MacOS :: MacOS X
Classifier: Operating System :: Microsoft :: Windows
Requires-Dist: numpy
